desktop.ini
pySynphasor/__init__.py
pySynphasor/crc.py
pySynphasor/desktop.ini
pySynphasor/synphasor.py
pySynphasor-0.1.0.dist-info/LICENSE
pySynphasor-0.1.0.dist-info/METADATA
pySynphasor-0.1.0.dist-info/WHEEL
pySynphasor-0.1.0.dist-info/desktop.ini
pySynphasor-0.1.0.dist-info/top_level.txt
pySynphasor-0.1.0.dist-info/RECORD
