Metadata-Version: 2.1
Name: pySynphasor
Version: 0.1.0
Summary: IEEE C37.118 Packet Manipulation Tool
Home-page: https://github.com/shuvangkardas/pySynphasor
Author: Shuvangkar Das
Author-email: shuvangkarcdas@gmail.com
Requires-Python: >=3.6
License-File: LICENSE
Requires-Dist: scapy
